justblockchain/__init__.py
justblockchain/justblockchain.py
justblockchain-1.0.1.dist-info/AUTHORS.rst
justblockchain-1.0.1.dist-info/LICENSE
justblockchain-1.0.1.dist-info/METADATA
justblockchain-1.0.1.dist-info/WHEEL
justblockchain-1.0.1.dist-info/top_level.txt
justblockchain-1.0.1.dist-info/RECORD
