Metadata-Version: 2.1
Name: justblockchain
Version: 1.0.1
Summary: A blockchain linker to help understand hash functions in blockchain
Home-page: https://github.com/koshikraj/justblockchain
Author: Koshik Raj
Author-email: koshik.raj@gmail.com
License: MIT license
Keywords: justblockchain
Platform: UNKNOWN
Classifier: Development Status :: 2 - Pre-Alpha
Classifier: Intended Audience :: Developers
Classifier: License :: OSI Approved :: MIT License
Classifier: Natural Language :: English
Classifier: Programming Language :: Python :: 2
Classifier: Programming Language :: Python :: 2.7
Classifier: Programming Language :: Python :: 3
Classifier: Programming Language :: Python :: 3.4
Classifier: Programming Language :: Python :: 3.5
Classifier: Programming Language :: Python :: 3.6
Requires-Dist: pycryptodome
